pylogger_slack/__init__.py
pylogger_slack/_config.py
pylogger_slack/logger.py
pylogger_slack/slack.py
pylogger_slack-0.1.0.dist-info/licenses/LICENSE
pylogger_slack-0.1.0.dist-info/METADATA
pylogger_slack-0.1.0.dist-info/WHEEL
pylogger_slack-0.1.0.dist-info/top_level.txt
pylogger_slack-0.1.0.dist-info/RECORD
