Metadata-Version: 2.4
Name: pylogger-slack
Version: 0.1.0
Summary: Python logging with an option to format it for YAML/JSON format with a support for Slack Notification. (Helpful for monitoring codebase in production/testing)
Author-email: Binay Kumar Pradhan <bpradhan.asli@gmail.com>
License-Expression: GPL-3.0
Project-URL: Repository, https://github.com/VinayIN/pylogger-slack.git
Project-URL: Documentation, https://pylogger-slack.readthedocs.io/latest/
Keywords: logger,python slack notification,logger yaml,logger json,python logging
Requires-Python: >=3.11
License-File: LICENSE
Requires-Dist: ecs-logging>=2.2.0
Requires-Dist: pyyaml>=6.0.2
Requires-Dist: slack-sdk>=3.35.0
Dynamic: license-file
